docs2db_api/__init__.py
docs2db_api/config.py
docs2db_api/database.py
docs2db_api/db_lifecycle.py
docs2db_api/docs2db_api.py
docs2db_api/embeddings.py
docs2db_api/exceptions.py
docs2db_api/rag/__init__.py
docs2db_api/rag/engine.py
docs2db_api/rag/llama_stack.py
docs2db_api/reranker.py
docs2db_api-0.3.1.dist-info/WHEEL
docs2db_api-0.3.1.dist-info/entry_points.txt
docs2db_api-0.3.1.dist-info/METADATA
docs2db_api-0.3.1.dist-info/RECORD
