Metadata-Version: 2.3
Name: docs2db-api
Version: 0.3.1
Summary: Query Docs2DB RAG databases with hybrid search and reranking
Keywords: rag,retrieval,embeddings,semantic-search,vector-search,hybrid-search,pgvector,postgresql,llm
Author: Ellis Low
Author-email: Ellis Low <elow@redhat.com>
License: Apache-2.0
Classifier: Development Status :: 4 - Beta
Classifier: Intended Audience :: Developers
Classifier: License :: OSI Approved :: Apache Software License
Classifier: Programming Language :: Python :: 3
Classifier: Programming Language :: Python :: 3.12
Classifier: Topic :: Scientific/Engineering :: Artificial Intelligence
Classifier: Topic :: Software Development :: Libraries :: Python Modules
Requires-Dist: cachetools>=6.1.0
Requires-Dist: docling>=2.42.1
Requires-Dist: httpx>=0.28.1
Requires-Dist: pgvector>=0.3.8
Requires-Dist: psycopg[binary]>=3.2.3
Requires-Dist: psycopg-pool>=3.2.6
Requires-Dist: pydantic-settings>=2.10.1
Requires-Dist: pyyaml>=6.0.1
Requires-Dist: rich>=14.0.0
Requires-Dist: structlog>=25.4.0
Requires-Dist: torch>=2.7.1
Requires-Dist: torchvision>=0.22.1
Requires-Dist: sentence-transformers>=3.3.0
Requires-Dist: tqdm>=4.67.1
Requires-Dist: xxhash>=3.5.0
Requires-Dist: fastapi>=0.116.1
Requires-Dist: uvicorn>=0.35.0
Requires-Dist: llama-stack>=0.2.20
Requires-Python: >=3.12, <3.13
Project-URL: Changelog, https://github.com/rhel-lightspeed/docs2db-api/blob/main/CHANGELOG.md
Project-URL: Documentation, https://github.com/rhel-lightspeed/docs2db-api#readme
Project-URL: Homepage, https://github.com/rhel-lightspeed/docs2db-api
Project-URL: Issues, https://github.com/rhel-lightspeed/docs2db-api/issues
Project-URL: Repository, https://github.com/rhel-lightspeed/docs2db-api
